Metadata-Version: 2.1
Name: googleads
Version: 47.0.0
Summary: Google Ads Python Client Library
Home-page: https://github.com/googleads/googleads-python-lib
Author: Mark Saniscalchi
Author-email: api.msaniscalchi@gmail.com
License: Apache License 2.0
Keywords: admanager google
Platform: any
Classifier: Intended Audience :: Developers
Classifier: License :: OSI Approved :: Apache Software License
Classifier: Programming Language :: Python :: 3.7
License-File: LICENSE
